CHANGES.rst
MANIFEST.in
README.rst
setup.py
docs/Makefile
docs/conf.py
docs/index.rst
docs/make.bat
pystrext/__init__.py
pystrext.egg-info/PKG-INFO
pystrext.egg-info/SOURCES.txt
pystrext.egg-info/dependency_links.txt
pystrext.egg-info/not-zip-safe
pystrext.egg-info/requires.txt
pystrext.egg-info/top_level.txt