Metadata-Version: 1.1
Name: pystrext
Version: 0.1.7
Summary: Python string extension
Home-page: https://pypi.python.org/pypi/pystrext
Author: Eric Lapouyade
Author-email: elapouya@gmail.com
License: LGPL 2.1
Keywords: string helpers
Platform: UNKNOWN
Classifier: Intended Audience :: Developers
Classifier: Development Status :: 4 - Beta
Classifier: Programming Language :: Python :: 2
Classifier: Programming Language :: Python :: 2.7
